{
  "galleries": [
        
    {
      "name": "Tomato Girl",
      "images": [
        {
          "order": 12,
          "url": "https://pub-2193ba767eaa45ac995c94988ff1de97.r2.dev/1782752032.jpg",
          "title": "Chic Casual Outfit Inspiration For Effortless Everyday Street Style",
          "category": "Tomato Girl",
          "date": "2026-06-30",
          "cover": false
        },
        {
          "order": 11,
          "url": "https://pub-2193ba767eaa45ac995c94988ff1de97.r2.dev/1782751671.jpg",
          "title": "Chic Oversized Outfit Aesthetic Perfect For Urban Fashion",
          "category": "Tomato Girl",
          "date": "2026-06-30",
          "cover": false
        }
      ]
    }
  ]
}
